open_clip/__init__.py
open_clip/bpe_simple_vocab_16e6.txt.gz
open_clip/factory.py
open_clip/loss.py
open_clip/model.py
open_clip/openai.py
open_clip/pretrained.py
open_clip/timm_model.py
open_clip/tokenizer.py
open_clip/transform.py
open_clip/utils.py
open_clip/version.py
open_clip/model_configs/RN101-quickgelu.json
open_clip/model_configs/RN101.json
open_clip/model_configs/RN50-quickgelu.json
open_clip/model_configs/RN50.json
open_clip/model_configs/RN50x16.json
open_clip/model_configs/RN50x4.json
open_clip/model_configs/ViT-B-16-plus-240.json
open_clip/model_configs/ViT-B-16-plus.json
open_clip/model_configs/ViT-B-16.json
open_clip/model_configs/ViT-B-32-plus-256.json
open_clip/model_configs/ViT-B-32-quickgelu.json
open_clip/model_configs/ViT-B-32.json
open_clip/model_configs/ViT-H-14.json
open_clip/model_configs/ViT-H-16.json
open_clip/model_configs/ViT-L-14-280.json
open_clip/model_configs/ViT-L-14-336.json
open_clip/model_configs/ViT-L-14.json
open_clip/model_configs/ViT-L-16-320.json
open_clip/model_configs/ViT-L-16.json
open_clip/model_configs/ViT-g-14.json
open_clip/model_configs/timm-efficientnetv2_rw_s.json
open_clip/model_configs/timm-resnet50d.json
open_clip/model_configs/timm-resnetaa50d.json
open_clip/model_configs/timm-resnetblur50.json
open_clip/model_configs/timm-swin_base_patch4_window7_224.json
open_clip/model_configs/timm-vit_base_patch16_224.json
open_clip/model_configs/timm-vit_base_patch32_224.json
open_clip/model_configs/timm-vit_small_patch16_224.json
open_clip_torch_any_py3-1.3.2.dist-info/LICENSE
open_clip_torch_any_py3-1.3.2.dist-info/METADATA
open_clip_torch_any_py3-1.3.2.dist-info/WHEEL
open_clip_torch_any_py3-1.3.2.dist-info/top_level.txt
open_clip_torch_any_py3-1.3.2.dist-info/RECORD
