Metadata-Version: 2.1
Name: open-clip-torch-any-py3
Version: 1.3.2
Summary: OpenCLIP
Home-page: https://github.com/mlfoundations/open_clip
Author: 
Author-email: 
License: UNKNOWN
Keywords: CLIP pretrained
Platform: UNKNOWN
Classifier: Development Status :: 3 - Alpha
Classifier: Intended Audience :: Education
Classifier: Intended Audience :: Science/Research
Classifier: License :: OSI Approved :: Apache Software License
Classifier: Programming Language :: Python :: 3.6
Classifier: Programming Language :: Python :: 3.7
Classifier: Programming Language :: Python :: 3.8
Classifier: Programming Language :: Python :: 3.9
Classifier: Programming Language :: Python :: 3.10
Classifier: Topic :: Scientific/Engineering
Classifier: Topic :: Scientific/Engineering :: Artificial Intelligence
Classifier: Topic :: Software Development
Classifier: Topic :: Software Development :: Libraries
Classifier: Topic :: Software Development :: Libraries :: Python Modules
Requires-Dist: torch (>=1.9)
Requires-Dist: torchvision
Requires-Dist: ftfy
Requires-Dist: regex
Requires-Dist: tqdm
